cewlio/__init__.py
cewlio/cli.py
cewlio/core.py
cewlio/extractors.py
cewlio-1.2.2.dist-info/licenses/LICENSE
tests/README.md
tests/TEST_DOCUMENTATION.md
tests/run_tests.py
tests/test_cewlio.py
cewlio-1.2.2.dist-info/METADATA
cewlio-1.2.2.dist-info/WHEEL
cewlio-1.2.2.dist-info/entry_points.txt
cewlio-1.2.2.dist-info/top_level.txt
cewlio-1.2.2.dist-info/RECORD
